openverse_api_client/.gitignore
openverse_api_client/__about__.py
openverse_api_client/__init__.py
openverse_api_client/async_client.py
openverse_api_client/literals.py
openverse_api_client/sync_client.py
openverse_api_client/endpoints/__init__.py
openverse_api_client/endpoints/auth.py
openverse_api_client/endpoints/base.py
openverse_api_client/endpoints/media.py
openverse_api_client/generate/__init__.py
openverse_api_client/generate/base.py
openverse_api_client/generate/python.py
openverse_api_client/generate/typescript.py
openverse_api_client/templates/python/client.py.jinja
openverse_api_client/templates/typescript/types.ts.jinja
openverse_api_client/templates/typescript/helpers/interface.ts.jinja
openverse_api_client-0.0.1.dist-info/METADATA
openverse_api_client-0.0.1.dist-info/WHEEL
openverse_api_client-0.0.1.dist-info/entry_points.txt
openverse_api_client-0.0.1.dist-info/licenses/LICENSE.txt
openverse_api_client-0.0.1.dist-info/RECORD
