Metadata-Version: 2.1
Name: openverse-api-client
Version: 0.0.1
Summary: Python client for the Openverse API
Project-URL: Documentation, https://git.sr.ht/~sara/openverse-api-client#readme
Project-URL: Issues, https://git.sr.ht/~sara/openverse-api-client/issues
Project-URL: Source, https://git.sr.ht/~sara/openverse-api-client
Author-email: sarayourfriend <24264157+sarayourfriend@users.noreply.github.com>
License-Expression: MIT
License-File: LICENSE.txt
Classifier: Development Status :: 4 - Beta
Classifier: Programming Language :: Python
Classifier: Programming Language :: Python :: 3.8
Classifier: Programming Language :: Python :: 3.9
Classifier: Programming Language :: Python :: 3.10
Classifier: Programming Language :: Python :: 3.11
Classifier: Programming Language :: Python :: 3.12
Classifier: Programming Language :: Python :: Implementation :: CPython
Classifier: Programming Language :: Python :: Implementation :: PyPy
Requires-Python: >=3.8
Requires-Dist: httpx
Provides-Extra: generator
Requires-Dist: jinja2; extra == 'generator'
